{
  "id": "220+ Resources for graphic designers",
  "name": "220+ Resources for graphic designers",
  "slug": "220-resources-for-graphic-designers",
  "description": "The ultimate graphic design resource package has arrived in the form of a Notion template, including over 220 free resources to take your design work to the next level. With our comprehensive template, you can say goodbye to the hassle of scouring the internet for the best graphic design resources. It's free to use and was created to assist graphic designers, artists, and creatives not to waste any more time searching for the perfect design resources. Keep all of your resources in one place, dow",
  "price": 0,
  "currency": "USD",
  "category": "template",
  "subcategory": "design",
  "creator": {
    "name": "Amira zairi",
    "url": "https://amirazairi.gumroad.com/"
  },
  "platform": "gumroad",
  "productUrl": "https://gumroad.com/a/962870099/gjfivd",
  "affiliateUrl": "https://gumroad.com/a/962870099/gjfivd",
  "hasAffiliate": true,
  "affiliateRate": "partner",
  "rating": 25,
  "ratingCount": 25,
  "salesCount": null,
  "tags": [],
  "useCases": [],
  "features": "Access for life (regular updates); More than 200 Resources; Save time on research.",
  "assessmentScore": 55,
  "recommendation": "RECOMMENDED",
  "status": "active",
  "dateAdded": "2026-01-12T20:47:12.710Z",
  "lastUpdated": "2026-01-12T20:47:12.710Z"
}