{
  "id": "Anime, Gradient and Shapes Notion Covers Packs",
  "name": "Anime, Gradient and Shapes Notion Covers Packs",
  "slug": "anime-gradient-and-shapes-notion-covers-packs",
  "description": "✨Make your Notion page unique and personalize it your way with these Notion Covers PacksThis includes170 Covers20 IconsDark Mode coversTwitter Banner compatibleHigh Quality &amp; OriginalAll assets are optimized to match your Notion workspace. Works perfectly in light and dark mode. Unlimited combinations. Mix and match to create your aesthetic page style or workspaceEnjoy! Looking forward to see your Notion creations!",
  "price": 0,
  "currency": "USD",
  "category": "template",
  "subcategory": "bundle",
  "creator": {
    "name": "Sam",
    "url": "https://samstoof.gumroad.com/"
  },
  "platform": "gumroad",
  "productUrl": "https://gumroad.com/a/962870099/cwfhq",
  "affiliateUrl": "https://gumroad.com/a/962870099/cwfhq",
  "hasAffiliate": true,
  "affiliateRate": "partner",
  "rating": 19,
  "ratingCount": 19,
  "salesCount": null,
  "tags": [],
  "useCases": [],
  "features": "Dark Mode covers; Twitter Banner compatible; High Quality & Original",
  "assessmentScore": 70,
  "recommendation": "HIGHLY RECOMMENDED",
  "status": "active",
  "dateAdded": "2026-01-12T20:47:12.880Z",
  "lastUpdated": "2026-01-12T20:47:12.880Z"
}