{
  "id": "Free AI Tools for Stunning Images, Videos, and Audio | Easy & Professional Content Creation",
  "name": "Free AI Tools for Stunning Images, Videos, and Audio | Easy & Professional Content Creation",
  "slug": "free-ai-tools-for-stunning-images-videos-and-audio-easy-professional-content-creation",
  "description": "AI Content-Master: Free Image, Video &amp; Audio AI Tools | Notion TemplateAre you looking to create captivating visuals, videos, and audio effortlessly? Look no further! The AI Content-Master includes 50+ free AI tools that offer everything you need to bring your creative ideas to life. Whether you're a professional, marketer, or creator, these tools are perfect to improve your content.Tools for:ImagesVideosAudioEach tool includes a brief summary and a direct link to its platform.As an addition",
  "price": 0,
  "currency": "USD",
  "category": "tool",
  "subcategory": "ai",
  "creator": {
    "name": "NotionPlates",
    "url": "https://notionplates.gumroad.com/"
  },
  "platform": "gumroad",
  "productUrl": "https://gumroad.com/a/962870099/ufmak",
  "affiliateUrl": "https://gumroad.com/a/962870099/ufmak",
  "hasAffiliate": true,
  "affiliateRate": "partner",
  "rating": 16,
  "ratingCount": 16,
  "salesCount": null,
  "tags": [],
  "useCases": [],
  "features": "",
  "assessmentScore": 55,
  "recommendation": "RECOMMENDED",
  "status": "active",
  "dateAdded": "2026-01-12T20:47:12.695Z",
  "lastUpdated": "2026-01-12T20:47:12.695Z"
}