{
  "id": "Meal Planner with Notion",
  "name": "Meal Planner with Notion",
  "slug": "meal-planner-with-notion",
  "description": "Do you ever find yourself struggling to plan your meals for the week? Or maybe you're always running out of ingredients at the grocery store? If so, then you need to check out the Meal Planner template!The Meal Planner template is an easy-to-use tool that can help you plan your meals for the week, make a grocery list based on your meal plan, keep track of your favorite recipes, and calculate your daily calorie intake. It's easy to use and can be customized to fit your needs.Here are some of the ",
  "price": 3,
  "currency": "USD",
  "category": "tool",
  "subcategory": "planner",
  "creator": {
    "name": "El Vairus Notion Templates",
    "url": "https://vairusstrategy.gumroad.com/"
  },
  "platform": "gumroad",
  "productUrl": "https://gumroad.com/a/962870099/qyjav",
  "affiliateUrl": "https://gumroad.com/a/962870099/qyjav",
  "hasAffiliate": true,
  "affiliateRate": "partner",
  "rating": 26,
  "ratingCount": 26,
  "salesCount": 264,
  "tags": [],
  "useCases": [],
  "features": "Save time: The Meal Planner template can help you save time by taking the guesswork out of meal planning.; Save money: The Meal Planner template can help you save money by helping you avoid wasting food.; Eat healthier: The Meal Planner template can help you eat healthier by making it easier to plan balanced meals.; Plan your meals for the week.; Make a grocery list based on your meal plan.; Keep track of your favorite recipes.; Calculate your daily calorie intake.; And much more!",
  "assessmentScore": 95,
  "recommendation": "HIGHLY RECOMMENDED",
  "status": "active",
  "dateAdded": "2026-01-12T20:47:12.828Z",
  "lastUpdated": "2026-01-12T20:47:12.828Z"
}