{
  "id": "Notion Habit Tracker for Free",
  "name": "Notion Habit Tracker for Free",
  "slug": "notion-habit-tracker-for-free",
  "description": "Boost Productivity and Achieve Your Goals with the Notion Habit Tracker TemplateDiscover the ultimate tool for personal growth and success! The Notion Habit Tracker Template empowers you to track and monitor your daily habits, enabling you to establish positive routines and achieve your goals.Habit TrackerMonthly ReportProgressbarDaily, Weekly, Monthly viewFAQs1. What is Notion?Notion is a comprehensive and fully-integrated workspace that simplifies note-taking, task management, project planning",
  "price": 0,
  "currency": "USD",
  "category": "tool",
  "subcategory": "planner",
  "creator": {
    "name": "Solt Wagner",
    "url": "https://soltwagner.gumroad.com/"
  },
  "platform": "gumroad",
  "productUrl": "https://gumroad.com/a/883590867/nyyql",
  "affiliateUrl": "https://gumroad.com/a/883590867/nyyql",
  "hasAffiliate": true,
  "affiliateRate": "partner",
  "rating": 57,
  "ratingCount": 57,
  "salesCount": null,
  "tags": [],
  "useCases": [],
  "features": "Habit Tracker; Monthly Report; Progressbar; Daily, Weekly, Monthly view",
  "assessmentScore": 75,
  "recommendation": "HIGHLY RECOMMENDED",
  "status": "active",
  "dateAdded": "2026-01-12T20:47:13.621Z",
  "lastUpdated": "2026-01-12T20:47:13.621Z"
}