{
  "id": "Notion for Sales Professionals: Online Course",
  "name": "Notion for Sales Professionals: Online Course",
  "slug": "notion-for-sales-professionals-online-course",
  "description": "Unlock the Full Potential of Notion for Sales Professionals!Elevate your productivity and efficiency with our comprehensive course designed for sales professionals. This course will take you from a basic understanding of Notion to mastering a fully functional workspace tailored for managing sales operations. Get ready to explore advanced features, integrations, and effective data management!Who is it For?This course is designed for sales professionals who have a basic understanding of Notion but",
  "price": 25,
  "currency": "USD",
  "category": "course",
  "subcategory": "crm",
  "creator": {
    "name": "Ian Dikhtiar",
    "url": "https://extycreate.gumroad.com/"
  },
  "platform": "gumroad",
  "productUrl": "https://gumroad.com/a/145902419/iktaa",
  "affiliateUrl": "https://gumroad.com/a/145902419/iktaa",
  "hasAffiliate": true,
  "affiliateRate": "partner",
  "rating": null,
  "ratingCount": null,
  "salesCount": null,
  "tags": [],
  "useCases": [],
  "features": "Skill Level:Intermediate; - Sales professionals looking to streamline their tasks and data management.; - Sales managers wanting to optimize team workflows.; - Sales teams aiming to improve collaboration and efficiency.; Basic understanding of Notion features; - Familiarity with sales processes; - Basic knowledge of data management; - Navigating the Notion Universe",
  "assessmentScore": 80,
  "recommendation": "HIGHLY RECOMMENDED",
  "status": "active",
  "dateAdded": "2026-01-12T20:47:13.346Z",
  "lastUpdated": "2026-01-12T20:47:13.346Z"
}