{
  "id": "Notion for Event Planners: Online Course",
  "name": "Notion for Event Planners: Online Course",
  "slug": "notion-for-event-planners-online-course",
  "description": "Transform Your Event Planning with Notion!Unlock the full potential of Notion to revolutionize your event planning process! This intermediate course is designed specifically for event planners who are ready to elevate their organizational skills and streamline their workflow. By the end of this course, you will have the tools and knowledge to create a comprehensive Notion dashboard tailored to your unique event planning needs. Get ready to transform chaos into clarity!Who is it For?This course i",
  "price": 25,
  "currency": "USD",
  "category": "course",
  "subcategory": "dashboard",
  "creator": {
    "name": "Ian Dikhtiar",
    "url": "https://extycreate.gumroad.com/"
  },
  "platform": "gumroad",
  "productUrl": "https://gumroad.com/a/145902419/cpahc",
  "affiliateUrl": "https://gumroad.com/a/145902419/cpahc",
  "hasAffiliate": true,
  "affiliateRate": "partner",
  "rating": null,
  "ratingCount": null,
  "salesCount": null,
  "tags": [],
  "useCases": [],
  "features": "Event planners looking to streamline their processes; - Professionals seeking to enhance their task management skills; - Individuals wanting to improve collaboration with stakeholders; Basic knowledge of Notion; - Familiarity with event planning processes; - Understanding of database concepts; Diving Deeper into Notion; 2. Crafting Your Event Planning Dashboard; 3. Automating Tasks with Formulas; 4. Integrating Notion with Other Tools",
  "assessmentScore": 80,
  "recommendation": "HIGHLY RECOMMENDED",
  "status": "active",
  "dateAdded": "2026-01-12T20:47:13.346Z",
  "lastUpdated": "2026-01-12T20:47:13.346Z"
}