{
  "id": "Notion Habit Tracker",
  "name": "Notion Habit Tracker",
  "slug": "notion-habit-tracker-14",
  "description": "Get a new habit in 30 days.Notion Habit tracker is a productivity tool that helps you develop and maintain good habits over a period of 30 days. It allows you to track your daily habits and monitor your progress as you work towards your goals.InformationTo use the habit tracker, you first create a list of the habits you want to focus on for the next 30 days. These habits could be anything from exercising regularly to reading a book each day. You can customize the habit tracker to fit your needs ",
  "price": 0,
  "currency": "USD",
  "category": "tool",
  "subcategory": "planner",
  "creator": {
    "name": "Design Freaks",
    "url": "https://dfreaks.gumroad.com/"
  },
  "platform": "gumroad",
  "productUrl": "https://gumroad.com/a/1051518675/dxrjx",
  "affiliateUrl": "https://gumroad.com/a/1051518675/dxrjx",
  "hasAffiliate": true,
  "affiliateRate": "partner",
  "rating": 9,
  "ratingCount": 9,
  "salesCount": null,
  "tags": [],
  "useCases": [],
  "features": "",
  "assessmentScore": 75,
  "recommendation": "HIGHLY RECOMMENDED",
  "status": "active",
  "dateAdded": "2026-01-12T20:47:13.598Z",
  "lastUpdated": "2026-01-12T20:47:13.598Z"
}