{
  "id": "Notion Link In Bio",
  "name": "Notion Link In Bio",
  "slug": "notion-link-in-bio",
  "description": "Get your own Link in Bio page using only Notion!Notion Link In Bio is designed to help you convert more profile link clicks with a cool Link In Bio page!How does it work? Duplicate the template into your own Notion Edit the template to your own preferences Add your own links, visuals &amp; even sections. Publish your Notion Link In bio to the world Better yet, pick a Notion website host and add a .com domain! Frequently Asked Questions What is Notion?Notion is a free-to-use single digital space ",
  "price": 0,
  "currency": "USD",
  "category": "template",
  "subcategory": "ai",
  "creator": {
    "name": "Pascio",
    "url": "https://pascio.gumroad.com/"
  },
  "platform": "gumroad",
  "productUrl": "https://gumroad.com/a/919154899/wxdfn",
  "affiliateUrl": "https://gumroad.com/a/919154899/wxdfn",
  "hasAffiliate": true,
  "affiliateRate": "partner",
  "rating": 103,
  "ratingCount": 103,
  "salesCount": null,
  "tags": [],
  "useCases": [],
  "features": "Duplicate the template into your own Notion; Edit the template to your own preferences; Add your own links, visuals & even sections.; Publish your Notion Link In bio to the world; Better yet, pick a Notion website host and add a .com domain!; Who are you?I am Pascio, official Notion Ambassador, Consultant & Creator of more than 50+ free & premium Notion templates that have served 200,000+ people across the globe.; Can I share this with anyone else?No. This product has a private license. If you wish to share it with someone, please direct them to this page.; Can I be your affiliate?Sure thing! You can sign up as an affiliatehere.",
  "assessmentScore": 75,
  "recommendation": "HIGHLY RECOMMENDED",
  "status": "active",
  "dateAdded": "2026-01-12T20:47:13.504Z",
  "lastUpdated": "2026-01-12T20:47:13.504Z"
}