{
  "id": "Notion Project Management for Free",
  "name": "Notion Project Management for Free",
  "slug": "notion-project-management-for-free-1",
  "description": "Boost Your Project Management Efficiency with Notion TemplateTake control of your projects and tasks today! Use our customizable Notion template to streamline your project management and achieve your goals faster. Start managing with ease and increase your productivity now!Project ManagementKanban BoardTask ManagementTimelineProject status progressbarFAQs1. What is Notion?Notion is a comprehensive and fully-integrated workspace that simplifies note-taking, task management, project planning, and ",
  "price": 0,
  "currency": "USD",
  "category": "template",
  "subcategory": "planner",
  "creator": {
    "name": "Solt Wagner",
    "url": "https://soltwagner.gumroad.com/"
  },
  "platform": "gumroad",
  "productUrl": "https://gumroad.com/a/883590867/ocfbzk",
  "affiliateUrl": "https://gumroad.com/a/883590867/ocfbzk",
  "hasAffiliate": true,
  "affiliateRate": "partner",
  "rating": 272,
  "ratingCount": 272,
  "salesCount": null,
  "tags": [],
  "useCases": [],
  "features": "Project Management; Kanban Board; Task Management; Project status progressbar",
  "assessmentScore": 75,
  "recommendation": "HIGHLY RECOMMENDED",
  "status": "active",
  "dateAdded": "2026-01-12T20:47:13.612Z",
  "lastUpdated": "2026-01-12T20:47:13.612Z"
}