{
  "id": "Notion Invoice Template",
  "name": "Notion Invoice Template",
  "slug": "notion-invoice-template-1",
  "description": "The Rolls-Royce of online invoicesInvoices are a simple, yet super important part of any business. And if you’re a freelancer, it’s really important that you find the best way to easily create, send &amp; store invoices. Some platforms allow you to create invoices, but why pay for a new tool when you can get them done in your favorite app.The great thing about having your invoices in Notion is that: you can easily modify them you can easily store them you can automate them (e.g. when lead is \"ho",
  "price": 0,
  "currency": "USD",
  "category": "tool",
  "subcategory": "crm",
  "creator": {
    "name": "Templates For Notion",
    "url": "https://ramesquinerie.gumroad.com/"
  },
  "platform": "gumroad",
  "productUrl": "https://gumroad.com/a/822660307/nyvcc",
  "affiliateUrl": "https://gumroad.com/a/822660307/nyvcc",
  "hasAffiliate": true,
  "affiliateRate": "partner",
  "rating": 29,
  "ratingCount": 29,
  "salesCount": null,
  "tags": [],
  "useCases": [],
  "features": "you can easily modify them; you can easily store them; you canautomate them(e.g. when lead is \"hot\", create new invoice); they can be integrated into your project management setup; Beautiful invoice template; Shareable as a mini-website; Invoice storage database",
  "assessmentScore": 75,
  "recommendation": "HIGHLY RECOMMENDED",
  "status": "active",
  "dateAdded": "2026-01-12T20:47:13.470Z",
  "lastUpdated": "2026-01-12T20:47:13.470Z"
}