{
  "id": "Notion Real Estate Template",
  "name": "Notion Real Estate Template",
  "slug": "notion-real-estate-template",
  "description": "Stop wasting time juggling tools.Start investing like a pro, in Notion.The Real Estate Hub Notion Template is an all-encompassing and powerful tool that has been meticulously crafted to assist real estate professionals in effectively managing their daily tasks, properties &amp; finances. This innovative template features 15+ distinct databases &amp; templates, each of which is expertly tailored to address a specific aspect of the real estate industry, providing you with the confidence you need t",
  "price": 0,
  "currency": "USD",
  "category": "tool",
  "subcategory": "dashboard",
  "creator": {
    "name": "Templates For Notion",
    "url": "https://ramesquinerie.gumroad.com/"
  },
  "platform": "gumroad",
  "productUrl": "https://gumroad.com/a/822660307/ztgll",
  "affiliateUrl": "https://gumroad.com/a/822660307/ztgll",
  "hasAffiliate": true,
  "affiliateRate": "partner",
  "rating": null,
  "ratingCount": null,
  "salesCount": null,
  "tags": [],
  "useCases": [],
  "features": "Contacts: This is basically your CRM for tenants, contractors, utilities, and others. Each contact can be associated with one or multiple properties.",
  "assessmentScore": 55,
  "recommendation": "RECOMMENDED",
  "status": "active",
  "dateAdded": "2026-01-12T20:47:13.476Z",
  "lastUpdated": "2026-01-12T20:47:13.476Z"
}