{
  "id": "On-Page SEO Checklist for 2024",
  "name": "On-Page SEO Checklist for 2024",
  "slug": "on-page-seo-checklist-for-2024",
  "description": "UPDATED FOR 2024\"It's an amazing resource, Josh Spilker! I can't wait to apply it to my new blog post later next week.\" -- Nneka Otika, content marketing writerImprove your on-page SEO with this handy checklist. I used it to help grow the Friday.app , Range.co, Tettra.com blog (and others!) gain lots of keywords. Here are Ahrefs charts: The Notion template includes: Checklist of items to check before publishingDescription and best practices behind each checklist itemA schedule to use with your t",
  "price": 7,
  "currency": "USD",
  "category": "tool",
  "subcategory": "planner",
  "creator": {
    "name": "Growth Content",
    "url": "https://growthcontent.gumroad.com/"
  },
  "platform": "gumroad",
  "productUrl": "https://gumroad.com/a/962870099/vEVgj",
  "affiliateUrl": "https://gumroad.com/a/962870099/vEVgj",
  "hasAffiliate": true,
  "affiliateRate": "partner",
  "rating": null,
  "ratingCount": null,
  "salesCount": 170,
  "tags": [],
  "useCases": [],
  "features": "Checklist of items to check before publishing; Description and best practices behind each checklist item; A schedule to use with your team to assign tasks",
  "assessmentScore": 60,
  "recommendation": "RECOMMENDED",
  "status": "active",
  "dateAdded": "2026-01-12T20:47:12.927Z",
  "lastUpdated": "2026-01-12T20:47:12.927Z"
}