{
  "id": "Portion of the Notion Athlete OS",
  "name": "Portion of the Notion Athlete OS",
  "slug": "portion-of-the-notion-athlete-os",
  "description": "Athlete OS - become the best version of yourselfAthlete OS is the Notion template that allows you to work out effectively. It supports you on your fitness journey like no other application can.Athlete OS got you covered ! Need exercises for a specific muscle group ? We have over 45 different ones. Need a place to organize articles , podcasts and videos ? Not a problem. Need a place to list your goals, a place to journal , to find cooking recipes and a place to stay motivated ? Athlete OS does ex",
  "price": 0,
  "currency": "USD",
  "category": "tool",
  "subcategory": "tracker",
  "creator": {
    "name": "Finn",
    "url": "https://vimfinn.gumroad.com/"
  },
  "platform": "gumroad",
  "productUrl": "https://gumroad.com/a/962870099/jxnoc",
  "affiliateUrl": "https://gumroad.com/a/962870099/jxnoc",
  "hasAffiliate": true,
  "affiliateRate": "partner",
  "rating": null,
  "ratingCount": null,
  "salesCount": null,
  "tags": [],
  "useCases": [],
  "features": "Exercises section ( 45 + exercises neatly organized into categories including  Leg, Athletic, Arm and Chest Exercises; Resources section ( organize everyting into Notebooks and Notes ); Journal + Habit Tracker ( write your thoughts ); 50% discount for the whole Notion Template",
  "assessmentScore": 55,
  "recommendation": "RECOMMENDED",
  "status": "active",
  "dateAdded": "2026-01-12T20:47:12.563Z",
  "lastUpdated": "2026-01-12T20:47:12.563Z"
}