{
  "id": "second-brain-notion-template-034",
  "name": "Second Brain Notion Template: The Most Popular Free PARA System",
  "slug": "second-brain-notion-template",
  "description": "Second Brain methodology inspired template",
  "price": 0,
  "currency": "USD",
  "creator": {
    "name": "Augmentor Academy",
    "url": ""
  },
  "platform": "gumroad",
  "productUrl": "https://paideiaxpraxis.gumroad.com/l/sHARJ?a=962870099",
  "affiliateUrl": "https://paideiaxpraxis.gumroad.com/l/sHARJ?a=962870099",
  "category": "template",
  "subcategory": "second brain",
  "tags": [
    "Second Brain",
    "Tasks",
    "Goals"
  ],
  "useCases": [
    "personal",
    "business",
    "students"
  ],
  "hasAffiliate": true,
  "affiliateRate": 30,
  "status": "active",
  "dateAdded": "2026-01-10",
  "lastUpdated": "2026-01-10"
}