{
  "id": "Single Page Resume - Free Notion Template",
  "name": "Single Page Resume - Free Notion Template",
  "slug": "single-page-resume-free-notion-template",
  "description": "A simple, elegant resume. Single page resume which covers- Bio - Objective- Experience- Education - Skills- Core Certifications- Online Certifications- Conference- Honors and Awards- Invited Talks - Workshop Participated- Contact - ReferenceDoes this work on the free version of Notion?Yes, it works with Notion free and pro plans.Can I share with my friends/team?No, this is a personal license for individual use.🤝 Affiliates: Contact: howtousenotion@gmail.com with your Gumroad Email ID.Connect wit",
  "price": 3.49,
  "currency": "USD",
  "category": "template",
  "subcategory": "ai",
  "creator": {
    "name": "How To Use Notion",
    "url": "https://howtousenotion.gumroad.com/"
  },
  "platform": "gumroad",
  "productUrl": "https://gumroad.com/a/962870099/DAUWW",
  "affiliateUrl": "https://gumroad.com/a/962870099/DAUWW",
  "hasAffiliate": true,
  "affiliateRate": "partner",
  "rating": 8,
  "ratingCount": 8,
  "salesCount": null,
  "tags": [],
  "useCases": [],
  "features": "",
  "assessmentScore": 70,
  "recommendation": "HIGHLY RECOMMENDED",
  "status": "active",
  "dateAdded": "2026-01-12T20:47:12.612Z",
  "lastUpdated": "2026-01-12T20:47:12.612Z"
}