{
  "id": "Notion Smart Goals Tracker",
  "name": "Notion Smart Goals Tracker",
  "slug": "smart-goals-tracker",
  "description": "Achieve Your Goals Smartly with Notion SMART Goals TrackerAn all-in-one Notion template to set goals, evaluate them, and set &amp; track habits to achieve them.What are SMART Goals?SMART Goals stands for Specific, Measurable, Actionable, Realistic, and Time-Bound Goals.S → SpecificThe mistake most people make while setting a goal (mostly long-term) is making it really vague. For instance, increasing typing speed. Instead, create a very specific goal.M → MeasurableOnce you have set a specific goa",
  "price": 21,
  "currency": "USD",
  "category": "template",
  "subcategory": "tracker",
  "creator": {
    "name": "Atul's Notion",
    "url": "https://atulacleaver.gumroad.com/"
  },
  "platform": "gumroad",
  "productUrl": "https://gumroad.com/a/962870099/ZUTkr",
  "affiliateUrl": "https://gumroad.com/a/962870099/ZUTkr",
  "hasAffiliate": true,
  "affiliateRate": "partner",
  "rating": 189,
  "ratingCount": 189,
  "salesCount": 108,
  "tags": [
    "Goals",
    "Habits"
  ],
  "useCases": [],
  "features": "",
  "assessmentScore": 110,
  "recommendation": "HIGHLY RECOMMENDED",
  "status": "active",
  "dateAdded": "October 23, 2022 7:08 AM",
  "lastUpdated": "2026-01-12T20:47:12.460Z"
}