{
  "id": "The Ultimate Notion Course for Student Success",
  "name": "The Ultimate Notion Course for Student Success",
  "slug": "the-ultimate-notion-course-for-student-success",
  "description": "Unlock Your Study Potential with Notion!Unlock the full potential of Notion and transform your study habits with 'The Ultimate Notion Course for Student Success.' This practical course is designed for students who have a basic understanding of Notion but are eager to elevate their productivity and organization skills. By the end of this course, you will have mastered advanced features of Notion, allowing you to create a personalized workspace that enhances your study routine and keeps your assig",
  "price": 25,
  "currency": "USD",
  "category": "course",
  "subcategory": "tracker",
  "creator": {
    "name": "Ian Dikhtiar",
    "url": "https://extycreate.gumroad.com/"
  },
  "platform": "gumroad",
  "productUrl": "https://gumroad.com/a/145902419/hvccsn",
  "affiliateUrl": "https://gumroad.com/a/145902419/hvccsn",
  "hasAffiliate": true,
  "affiliateRate": "partner",
  "rating": null,
  "ratingCount": null,
  "salesCount": null,
  "tags": [],
  "useCases": [],
  "features": "Students seeking better study organization; - Educators looking to enhance their teaching methods; - Study groups aiming for effective collaboration; Basic understanding of Notion interface; - Familiarity with digital note-taking; - Basic organizational skills; - Mastering the Notion Interface; - Building Your Study System; - Integrating Notion with Other Tools",
  "assessmentScore": 80,
  "recommendation": "HIGHLY RECOMMENDED",
  "status": "active",
  "dateAdded": "2026-01-12T20:47:13.321Z",
  "lastUpdated": "2026-01-12T20:47:13.321Z"
}