{
  "id": "The Mastery Checklist",
  "name": "The Mastery Checklist",
  "slug": "the-mastery-checklist",
  "description": "Listen up Fellow GlitchForget your boring to-do lists. They’re for the slaves.Utilize a Mastery Checklist. Become a master of your craft. And ultimately you’ll be master of your own life.Mastery Checklist is a Notion Template which you can easily duplicate and cater it towards your daily life 🔄ps: You’ll also learn the philosophy behind the mastery checklist shared by Luke Belmar in the Notion Template.PLAN → EXECUTE → ITERATE",
  "price": 0,
  "currency": "USD",
  "category": "course",
  "subcategory": "planner",
  "creator": {
    "name": "VISIONARY",
    "url": "https://fellowglitch.gumroad.com/"
  },
  "platform": "gumroad",
  "productUrl": "https://gumroad.com/a/962870099/mvmqo",
  "affiliateUrl": "https://gumroad.com/a/962870099/mvmqo",
  "hasAffiliate": true,
  "affiliateRate": "partner",
  "rating": 30,
  "ratingCount": 30,
  "salesCount": null,
  "tags": [],
  "useCases": [],
  "features": "",
  "assessmentScore": 55,
  "recommendation": "RECOMMENDED",
  "status": "active",
  "dateAdded": "2026-01-12T20:47:12.881Z",
  "lastUpdated": "2026-01-12T20:47:12.881Z"
}