{
  "id": "To-do List Template",
  "name": "To-do List Template",
  "slug": "to-do-list-template",
  "description": "Simple. Minimal. Effective. Track your daily tasks and progress with ease.This Notion To-Do List Template is a simple yet powerful way to manage your daily tasks. Perfect for anyone who loves a clean and minimal setup, it helps you stay on top of your goals without the overwhelm.✅ Features: A simple to-do list table to organize tasks by priority. A built-in calendar view to track your daily task completion and stay consistent. Minimal, distraction-free design that’s easy to use. Whether you’re a",
  "price": 0,
  "currency": "USD",
  "category": "template",
  "subcategory": "planner",
  "creator": {
    "name": "Poonam Sharma",
    "url": "https://poonam4gumroad.gumroad.com/"
  },
  "platform": "gumroad",
  "productUrl": "https://gumroad.com/a/962870099/qchzz",
  "affiliateUrl": "https://gumroad.com/a/962870099/qchzz",
  "hasAffiliate": true,
  "affiliateRate": "partner",
  "rating": 35,
  "ratingCount": 35,
  "salesCount": null,
  "tags": [],
  "useCases": [],
  "features": "A simpleto-do list tableto organize tasks by priority.; A built-incalendar viewto track your daily task completion and stay consistent.; Minimal, distraction-free design that’s easy to use.; Tracking daily tasks; Staying consistent with habits & goals; Visualizing progress over time",
  "assessmentScore": 55,
  "recommendation": "RECOMMENDED",
  "status": "active",
  "dateAdded": "2026-01-12T20:47:13.024Z",
  "lastUpdated": "2026-01-12T20:47:13.024Z"
}