{
  "id": "Ultimate Notion Accounting, Bookkeeping  and Finance Template",
  "name": "Ultimate Notion Accounting, Bookkeeping  and Finance Template",
  "slug": "ultimate-notion-accounting-bookkeeping-and-finance-template",
  "description": "Ultimate Accounting and Finance for Notion: Your Complete Financial Management SolutionIntroducing Ultimate Accounting and Finance, a comprehensive template meticulously designed for Notion to revolutionize your financial management processes. Seamlessly handle all aspects of accounting, bookkeeping, and finance, empowering you to take control of your financial destiny.An In-Depth Look at Ultimate Accounting and FinanceThis template serves as your centralized hub for all your financial activitie",
  "price": 0,
  "currency": "USD",
  "category": "template",
  "subcategory": "dashboard",
  "creator": {
    "name": "Lexy",
    "url": "https://lexychat.gumroad.com/"
  },
  "platform": "gumroad",
  "productUrl": "https://gumroad.com/a/962870099/vyclu",
  "affiliateUrl": "https://gumroad.com/a/962870099/vyclu",
  "hasAffiliate": true,
  "affiliateRate": "partner",
  "rating": 80,
  "ratingCount": 80,
  "salesCount": 322,
  "tags": [],
  "useCases": [],
  "features": "",
  "assessmentScore": 85,
  "recommendation": "HIGHLY RECOMMENDED",
  "status": "active",
  "dateAdded": "2026-01-12T20:47:12.681Z",
  "lastUpdated": "2026-01-12T20:47:12.681Z"
}